recordinality.py
recordinality-0.0.4.dist-info/DESCRIPTION.rst
recordinality-0.0.4.dist-info/METADATA
recordinality-0.0.4.dist-info/RECORD
recordinality-0.0.4.dist-info/WHEEL
recordinality-0.0.4.dist-info/entry_points.txt
recordinality-0.0.4.dist-info/metadata.json
recordinality-0.0.4.dist-info/top_level.txt
