Metadata-Version: 2.0
Name: recordinality
Version: 0.0.4
Summary: A Python implementation of the Recordinality sketch
Home-page: https://github.com/zacharyvoase/recordinality
Author: Zachary Voase
Author-email: zack@meat.io
License: Unlicense
Platform: UNKNOWN
Classifier: Development Status :: 3 - Alpha
Classifier: Intended Audience :: Developers
Classifier: License :: Public Domain
Classifier: Programming Language :: Python :: 2
Classifier: Programming Language :: Python :: 2.7
Classifier: Programming Language :: Python :: 3
Classifier: Programming Language :: Python :: 3.6
Requires-Dist: csiphash (>=0.0.5)
Requires-Dist: cskipdict (>=0.0.4)
Provides-Extra: test
Requires-Dist: coverage; extra == 'test'
